display/__init__.py
display/rich_demo.py
neuro_deploy/__init__.py
neuro_deploy/credentials.py
neuro_deploy/model.py
neuro_deploy/users.py
process/__init__.py
process/nd_access.py
process/nd_config.py
process/nd_token.py
queries/__init__.py
queries/credentials.py
queries/model.py
queries/users.py
sub_cmd/__init__.py
sub_cmd/config.py
sub_cmd/credentials.py
sub_cmd/model.py
sub_cmd/users.py
utils/__init__.py
utils/file.py
utils/query.py
neuro_deploy-0.3.dist-info/METADATA
neuro_deploy-0.3.dist-info/WHEEL
neuro_deploy-0.3.dist-info/top_level.txt
neuro_deploy-0.3.dist-info/RECORD
