Metadata-Version: 2.1
Name: neuro-deploy
Version: 0.3
Summary: neuro deploy SDK
Author: maher_naija
Classifier: Programming Language :: Python :: 3
Classifier: License :: OSI Approved :: MIT License
Classifier: Operating System :: OS Independent
Requires-Python: >=3.6
